tongliao/__init__.py
tongliao/collect_countries_area.py
tongliao/collect_countries_people.py
tongliao/collect_data.py
tongliao/core.py
tongliao/country2tongliao.py
tongliao-0.0.1.dist-info/METADATA
tongliao-0.0.1.dist-info/WHEEL
tongliao-0.0.1.dist-info/top_level.txt
tongliao-0.0.1.dist-info/RECORD
