Metadata-Version: 2.1
Name: tongliao
Version: 0.0.1
Summary: 通辽转换器！
Home-page: https://github.com/nemo2011/bilibili-api
Author: Nemo2011
License: GPLv3+
Classifier: License :: OSI Approved :: GNU General Public License v3 or later (GPLv3+)
Classifier: Programming Language :: Python :: 3.6
Classifier: Programming Language :: Python :: 3.7
Classifier: Programming Language :: Python :: 3.8
Classifier: Programming Language :: Python :: 3.9
Classifier: Programming Language :: Python :: 3.10
Requires-Python: >=3.6
